<?xml version="1.0" encoding="windows-1251"?>
<Gameplay>
  <Player id="1" name="Igor" symbol="X"/>
  <Player id="2" name="Anna" symbol="O"/>
  <Game>
    <Step num="1" playerId="1">22</Step>
    <Step num="2" playerId="2">13</Step>
    <Step num="3" playerId="1">31</Step>
    <Step num="4" playerId="2">11</Step>
    <Step num="5" playerId="1">12</Step>
    <Step num="6" playerId="2">33</Step>
    <Step num="7" playerId="1">23</Step>
    <Step num="8" playerId="2">21</Step>
    <Step num="9" playerId="1">32</Step>
  </Game>
  <GameResult><Player id="1" name="Igor" symbol="X"/></GameResult>
</Gameplay>